<?xml version="1.0" encoding="UTF-8"?>
<list xmlns:xsi="http://www.w3.org/2001/XMLSchema-instance"
      xmlns="http://l2j.org"
      xsi:schemaLocation="http://l2j.org multisell.xsd"
      apply-taxes="true">
    <npcs>
        34053 <!-- Attribute Master Svein -->
    </npcs>
    <item>
        <ingredient id="91125" count="500"/> <!-- Ignis' Breath -->
        <ingredient id="57" count="2000000"/> <!-- Adena -->
        <production id="91129"/> <!-- Agathion Ignis -->
    </item>
    <item>
        <ingredient id="91126"/> <!-- Nebula’s Breath-->
        <ingredient id="57" count="2000000"/> <!-- Adena -->
        <production id="91130"/> <!-- Agathion Nebula -->
    </item>
    <item>
        <ingredient id="91127"/> <!-- Procella’s  Breath-->
        <ingredient id="57" count="2000000"/> <!-- Adena -->
        <production id="91131"/> <!-- Agathion Procella -->
    </item>
    <item>
        <ingredient id="91128"/> <!-- Petram’s Breath-->
        <ingredient id="57" count="2000000"/> <!-- Adena -->
        <production id="91132"/> <!-- Agathion Petram -->
    </item>
</list>