<?xml version="1.0" encoding="UTF-8" standalone="no"?>
<list xmlns:xsi="http://www.w3.org/2001/XMLSchema-instance" xmlns="http://l2j.org" xsi:schemaLocation="http://l2j.org skills.xsd">
    <skill id="46300" name="Skill Range Decrease 65 per">
        <!--  -->
        <icon initial="icon.skill0000"/>
        <attributes/>
        <target/>
    </skill>
    <skill id="46301" name="Skill Range Decrease 70 per">
        <!--  -->
        <icon initial="icon.skill0000"/>
        <attributes/>
        <target/>
    </skill>
    <skill id="46302" name="Skill Range Decrease 75 per">
        <!--  -->
        <icon initial="icon.skill0000"/>
        <attributes/>
        <target/>
    </skill>
    <skill id="46303" name="Skill Range Decrease 80 per">
        <!--  -->
        <icon initial="icon.skill0000"/>
        <attributes/>
        <target/>
    </skill>
    <skill id="46304" name="Skill Range Decrease 85 per">
        <!--  -->
        <icon initial="icon.skill0000"/>
        <attributes/>
        <target/>
    </skill>
    <skill id="46305" name="Skill Range Decrease 90 per">
        <!--  -->
        <icon initial="icon.skill0000"/>
        <attributes/>
        <target/>
    </skill>
    <skill id="46306" name="Skill Range Decrease 95 per">
        <!--  -->
        <icon initial="icon.skill0000"/>
        <attributes/>
        <target/>
    </skill>
    <skill id="46307" name="Skill Range Decrease 100 per">
        <!--  -->
        <icon initial="icon.skill0000"/>
        <attributes/>
        <target/>
    </skill>
    <skill id="46308" name="MP Consumption Decrease 5 per">
        <!-- MP Consumption Decrease -5% -->
        <icon initial="icon.skill0000"/>
        <attributes/>
        <target/>
    </skill>
    <skill id="46309" name="MP Consumption Decrease 10 per">
        <!--  -->
        <icon initial="icon.skill0000"/>
        <attributes/>
        <target/>
    </skill>
    <skill id="46310" name="MP Consumption Decrease 15 per">
        <!--  -->
        <icon initial="icon.skill0000"/>
        <attributes/>
        <target/>
    </skill>
    <skill id="46311" name="MP Consumption Decrease 20 per">
        <!--  -->
        <icon initial="icon.skill0000"/>
        <attributes/>
        <target/>
    </skill>
    <skill id="46312" name="MP Consumption Decrease 25 per">
        <!--  -->
        <icon initial="icon.skill0000"/>
        <attributes/>
        <target/>
    </skill>
    <skill id="46313" name="MP Consumption Decrease 30 per">
        <!--  -->
        <icon initial="icon.skill0000"/>
        <attributes/>
        <target/>
    </skill>
    <skill id="46314" name="MP Consumption Decrease 35 per">
        <!--  -->
        <icon initial="icon.skill0000"/>
        <attributes/>
        <target/>
    </skill>
    <skill id="46315" name="MP Consumption Decrease 40 per">
        <!--  -->
        <icon initial="icon.skill0000"/>
        <attributes/>
        <target/>
    </skill>
    <skill id="46316" name="MP Consumption Decrease 45 per">
        <!--  -->
        <icon initial="icon.skill0000"/>
        <attributes/>
        <target/>
    </skill>
    <skill id="46317" name="MP Consumption Decrease 50 per">
        <!--  -->
        <icon initial="icon.skill0000"/>
        <attributes/>
        <target/>
    </skill>
    <skill id="46318" name="MP Consumption Decrease 55 per">
        <!--  -->
        <icon initial="icon.skill0000"/>
        <attributes/>
        <target/>
    </skill>
    <skill id="46319" name="MP Consumption Decrease 60 per">
        <!--  -->
        <icon initial="icon.skill0000"/>
        <attributes/>
        <target/>
    </skill>
    <skill id="46320" name="MP Consumption Decrease 65 per">
        <!--  -->
        <icon initial="icon.skill0000"/>
        <attributes/>
        <target/>
    </skill>
    <skill id="46321" name="MP Consumption Decrease 70 per">
        <!--  -->
        <icon initial="icon.skill0000"/>
        <attributes/>
        <target/>
    </skill>
    <skill id="46322" name="MP Consumption Decrease 75 per">
        <!--  -->
        <icon initial="icon.skill0000"/>
        <attributes/>
        <target/>
    </skill>
    <skill id="46323" name="MP Consumption Decrease 80 per">
        <!--  -->
        <icon initial="icon.skill0000"/>
        <attributes/>
        <target/>
    </skill>
    <skill id="46324" name="MP Consumption Decrease 85 per">
        <!--  -->
        <icon initial="icon.skill0000"/>
        <attributes/>
        <target/>
    </skill>
    <skill id="46325" name="MP Consumption Decrease 90 per">
        <!--  -->
        <icon initial="icon.skill0000"/>
        <attributes/>
        <target/>
    </skill>
    <skill id="46326" name="MP Consumption Decrease 95 per">
        <!--  -->
        <icon initial="icon.skill0000"/>
        <attributes/>
        <target/>
    </skill>
    <skill id="46327" name="MP Consumption Decrease 100 per">
        <!--  -->
        <icon initial="icon.skill0000"/>
        <attributes/>
        <target/>
    </skill>
    <skill id="46328" name="Attack Critical Damage Decrease 5 per">
        <!-- Attack Critical Damage Decrease -5% -->
        <icon initial="icon.skill0000"/>
        <attributes/>
        <target/>
    </skill>
    <skill id="46329" name="Attack Critical Damage Decrease 10 per">
        <!--  -->
        <icon initial="icon.skill0000"/>
        <attributes/>
        <target/>
    </skill>
    <skill id="46330" name="Attack Critical Damage Decrease 15 per">
        <!--  -->
        <icon initial="icon.skill0000"/>
        <attributes/>
        <target/>
    </skill>
    <skill id="46331" name="Attack Critical Damage Decrease 20 per">
        <!--  -->
        <icon initial="icon.skill0000"/>
        <attributes/>
        <target/>
    </skill>
    <skill id="46332" name="Attack Critical Damage Decrease 25 per">
        <!--  -->
        <icon initial="icon.skill0000"/>
        <attributes/>
        <target/>
    </skill>
    <skill id="46333" name="Attack Critical Damage Decrease 30 per">
        <!--  -->
        <icon initial="icon.skill0000"/>
        <attributes/>
        <target/>
    </skill>
    <skill id="46334" name="Attack Critical Damage Decrease 35 per">
        <!--  -->
        <icon initial="icon.skill0000"/>
        <attributes/>
        <target/>
    </skill>
    <skill id="46335" name="Attack Critical Damage Decrease 40 per">
        <!--  -->
        <icon initial="icon.skill0000"/>
        <attributes/>
        <target/>
    </skill>
    <skill id="46336" name="Attack Critical Damage Decrease 45 per">
        <!--  -->
        <icon initial="icon.skill0000"/>
        <attributes/>
        <target/>
    </skill>
    <skill id="46337" name="Attack Critical Damage Decrease 50 per">
        <!--  -->
        <icon initial="icon.skill0000"/>
        <attributes/>
        <target/>
    </skill>
    <skill id="46338" name="Attack Critical Damage Decrease 55 per">
        <!--  -->
        <icon initial="icon.skill0000"/>
        <attributes/>
        <target/>
    </skill>
    <skill id="46339" name="Attack Critical Damage Decrease 60 per">
        <!--  -->
        <icon initial="icon.skill0000"/>
        <attributes/>
        <target/>
    </skill>
    <skill id="46340" name="Attack Critical Damage Decrease 65 per">
        <!--  -->
        <icon initial="icon.skill0000"/>
        <attributes/>
        <target/>
    </skill>
    <skill id="46341" name="Attack Critical Damage Decrease 70 per">
        <!--  -->
        <icon initial="icon.skill0000"/>
        <attributes/>
        <target/>
    </skill>
    <skill id="46342" name="Attack Critical Damage Decrease 75 per">
        <!--  -->
        <icon initial="icon.skill0000"/>
        <attributes/>
        <target/>
    </skill>
    <skill id="46343" name="Attack Critical Damage Decrease 80 per">
        <!--  -->
        <icon initial="icon.skill0000"/>
        <attributes/>
        <target/>
    </skill>
    <skill id="46344" name="Attack Critical Damage Decrease 85 per">
        <!--  -->
        <icon initial="icon.skill0000"/>
        <attributes/>
        <target/>
    </skill>
    <skill id="46345" name="Attack Critical Damage Decrease 90 per">
        <!--  -->
        <icon initial="icon.skill0000"/>
        <attributes/>
        <target/>
    </skill>
    <skill id="46346" name="Attack Critical Damage Decrease 95 per">
        <!--  -->
        <icon initial="icon.skill0000"/>
        <attributes/>
        <target/>
    </skill>
    <skill id="46347" name="Attack Critical Damage Decrease 100 per">
        <!--  -->
        <icon initial="icon.skill0000"/>
        <attributes/>
        <target/>
    </skill>
    <skill id="46348" name="Attack Critical Damage Decrease (Shield) 5 per">
        <!-- Attack Critical Damage Decrease (Shield) -5% -->
        <icon initial="icon.skill0000"/>
        <attributes/>
        <target/>
    </skill>
    <skill id="46349" name="Attack Critical Damage Decrease (Shield) 10 per">
        <!--  -->
        <icon initial="icon.skill0000"/>
        <attributes/>
        <target/>
    </skill>
    <skill id="46350" name="Attack Critical Damage Decrease (Shield) 15 per">
        <!--  -->
        <icon initial="icon.skill0000"/>
        <attributes/>
        <target/>
    </skill>
    <skill id="46351" name="Attack Critical Damage Decrease (Shield) 20 per">
        <!--  -->
        <icon initial="icon.skill0000"/>
        <attributes/>
        <target/>
    </skill>
    <skill id="46352" name="Attack Critical Damage Decrease (Shield) 25 per">
        <!--  -->
        <icon initial="icon.skill0000"/>
        <attributes/>
        <target/>
    </skill>
    <skill id="46353" name="Attack Critical Damage Decrease (Shield) 30 per">
        <!--  -->
        <icon initial="icon.skill0000"/>
        <attributes/>
        <target/>
    </skill>
    <skill id="46354" name="Attack Critical Damage Decrease (Shield) 35 per">
        <!--  -->
        <icon initial="icon.skill0000"/>
        <attributes/>
        <target/>
    </skill>
    <skill id="46355" name="Attack Critical Damage Decrease (Shield) 40 per">
        <!--  -->
        <icon initial="icon.skill0000"/>
        <attributes/>
        <target/>
    </skill>
    <skill id="46356" name="Attack Critical Damage Decrease (Shield) 45 per">
        <!--  -->
        <icon initial="icon.skill0000"/>
        <attributes/>
        <target/>
    </skill>
    <skill id="46357" name="Attack Critical Damage Decrease (Shield) 50 per">
        <!--  -->
        <icon initial="icon.skill0000"/>
        <attributes/>
        <target/>
    </skill>
    <skill id="46358" name="Attack Critical Damage Decrease (Shield) 55 per">
        <!--  -->
        <icon initial="icon.skill0000"/>
        <attributes/>
        <target/>
    </skill>
    <skill id="46359" name="Attack Critical Damage Decrease (Shield) 60 per">
        <!--  -->
        <icon initial="icon.skill0000"/>
        <attributes/>
        <target/>
    </skill>
    <skill id="46360" name="Attack Critical Damage Decrease (Shield) 65 per">
        <!--  -->
        <icon initial="icon.skill0000"/>
        <attributes/>
        <target/>
    </skill>
    <skill id="46361" name="Attack Critical Damage Decrease (Shield) 70 per">
        <!--  -->
        <icon initial="icon.skill0000"/>
        <attributes/>
        <target/>
    </skill>
    <skill id="46362" name="Attack Critical Damage Decrease (Shield) 75 per">
        <!--  -->
        <icon initial="icon.skill0000"/>
        <attributes/>
        <target/>
    </skill>
    <skill id="46363" name="Attack Critical Damage Decrease (Shield) 80 per">
        <!--  -->
        <icon initial="icon.skill0000"/>
        <attributes/>
        <target/>
    </skill>
    <skill id="46364" name="Attack Critical Damage Decrease (Shield) 85 per">
        <!--  -->
        <icon initial="icon.skill0000"/>
        <attributes/>
        <target/>
    </skill>
    <skill id="46365" name="Attack Critical Damage Decrease (Shield) 90 per">
        <!--  -->
        <icon initial="icon.skill0000"/>
        <attributes/>
        <target/>
    </skill>
    <skill id="46366" name="Attack Critical Damage Decrease (Shield) 95 per">
        <!--  -->
        <icon initial="icon.skill0000"/>
        <attributes/>
        <target/>
    </skill>
    <skill id="46367" name="Attack Critical Damage Decrease (Shield) 100 per">
        <!--  -->
        <icon initial="icon.skill0000"/>
        <attributes/>
        <target/>
    </skill>
    <skill id="46368" name="Bow Atk. Spd. Decrease 5 per">
        <!-- Bow Atk. Spd. Decrease -5% -->
        <icon initial="icon.skill0000"/>
        <attributes/>
        <target/>
    </skill>
    <skill id="46369" name="Bow Atk. Spd. Decrease 10 per">
        <!--  -->
        <icon initial="icon.skill0000"/>
        <attributes/>
        <target/>
    </skill>
    <skill id="46370" name="Bow Atk. Spd. Decrease 15 per">
        <!--  -->
        <icon initial="icon.skill0000"/>
        <attributes/>
        <target/>
    </skill>
    <skill id="46371" name="Bow Atk. Spd. Decrease 20 per">
        <!--  -->
        <icon initial="icon.skill0000"/>
        <attributes/>
        <target/>
    </skill>
    <skill id="46372" name="Bow Atk. Spd. Decrease 25 per">
        <!--  -->
        <icon initial="icon.skill0000"/>
        <attributes/>
        <target/>
    </skill>
    <skill id="46373" name="Bow Atk. Spd. Decrease 30 per">
        <!--  -->
        <icon initial="icon.skill0000"/>
        <attributes/>
        <target/>
    </skill>
    <skill id="46374" name="Bow Atk. Spd. Decrease 35 per">
        <!--  -->
        <icon initial="icon.skill0000"/>
        <attributes/>
        <target/>
    </skill>
    <skill id="46375" name="Bow Atk. Spd. Decrease 40 per">
        <!--  -->
        <icon initial="icon.skill0000"/>
        <attributes/>
        <target/>
    </skill>
    <skill id="46376" name="Bow Atk. Spd. Decrease 45 per">
        <!--  -->
        <icon initial="icon.skill0000"/>
        <attributes/>
        <target/>
    </skill>
    <skill id="46377" name="Bow Atk. Spd. Decrease 50 per">
        <!--  -->
        <icon initial="icon.skill0000"/>
        <attributes/>
        <target/>
    </skill>
    <skill id="46378" name="Bow Atk. Spd. Decrease 55 per">
        <!--  -->
        <icon initial="icon.skill0000"/>
        <attributes/>
        <target/>
    </skill>
    <skill id="46379" name="Bow Atk. Spd. Decrease 60 per">
        <!--  -->
        <icon initial="icon.skill0000"/>
        <attributes/>
        <target/>
    </skill>
    <skill id="46380" name="Bow Atk. Spd. Decrease 65 per">
        <!--  -->
        <icon initial="icon.skill0000"/>
        <attributes/>
        <target/>
    </skill>
    <skill id="46381" name="Bow Atk. Spd. Decrease 70 per">
        <!--  -->
        <icon initial="icon.skill0000"/>
        <attributes/>
        <target/>
    </skill>
    <skill id="46382" name="Bow Atk. Spd. Decrease 75 per">
        <!--  -->
        <icon initial="icon.skill0000"/>
        <attributes/>
        <target/>
    </skill>
    <skill id="46383" name="Bow Atk. Spd. Decrease 80 per">
        <!--  -->
        <icon initial="icon.skill0000"/>
        <attributes/>
        <target/>
    </skill>
    <skill id="46384" name="Bow Atk. Spd. Decrease 85 per">
        <!--  -->
        <icon initial="icon.skill0000"/>
        <attributes/>
        <target/>
    </skill>
    <skill id="46385" name="Bow Atk. Spd. Decrease 90 per">
        <!--  -->
        <icon initial="icon.skill0000"/>
        <attributes/>
        <target/>
    </skill>
    <skill id="46386" name="Bow Atk. Spd. Decrease 95 per">
        <!--  -->
        <icon initial="icon.skill0000"/>
        <attributes/>
        <target/>
    </skill>
    <skill id="46387" name="Bow Atk. Spd. Decrease 100 per">
        <!--  -->
        <icon initial="icon.skill0000"/>
        <attributes/>
        <target/>
    </skill>
    <skill id="46388" name="Fall Damage/ Night Accuracy Decrease 5 per">
        <!-- Fall Damage/ Night Accuracy Decrease -5% -->
        <icon initial="icon.skill0000"/>
        <attributes/>
        <target/>
    </skill>
    <skill id="46389" name="Fall Damage/ Night Accuracy Decrease 10 per">
        <!--  -->
        <icon initial="icon.skill0000"/>
        <attributes/>
        <target/>
    </skill>
    <skill id="46390" name="Fall Damage/ Night Accuracy Decrease 15 per">
        <!--  -->
        <icon initial="icon.skill0000"/>
        <attributes/>
        <target/>
    </skill>
    <skill id="46391" name="Fall Damage/ Night Accuracy Decrease 20 per">
        <!--  -->
        <icon initial="icon.skill0000"/>
        <attributes/>
        <target/>
    </skill>
    <skill id="46392" name="Fall Damage/ Night Accuracy Decrease 25 per">
        <!--  -->
        <icon initial="icon.skill0000"/>
        <attributes/>
        <target/>
    </skill>
    <skill id="46393" name="Fall Damage/ Night Accuracy Decrease 30 per">
        <!--  -->
        <icon initial="icon.skill0000"/>
        <attributes/>
        <target/>
    </skill>
    <skill id="46394" name="Fall Damage/ Night Accuracy Decrease 35 per">
        <!--  -->
        <icon initial="icon.skill0000"/>
        <attributes/>
        <target/>
    </skill>
    <skill id="46395" name="Fall Damage/ Night Accuracy Decrease 40 per">
        <!--  -->
        <icon initial="icon.skill0000"/>
        <attributes/>
        <target/>
    </skill>
    <skill id="46396" name="Fall Damage/ Night Accuracy Decrease 45 per">
        <!--  -->
        <icon initial="icon.skill0000"/>
        <attributes/>
        <target/>
    </skill>
    <skill id="46397" name="Fall Damage/ Night Accuracy Decrease 50 per">
        <!--  -->
        <icon initial="icon.skill0000"/>
        <attributes/>
        <target/>
    </skill>
    <skill id="46398" name="Fall Damage/ Night Accuracy Decrease 55 per">
        <!--  -->
        <icon initial="icon.skill0000"/>
        <attributes/>
        <target/>
    </skill>
    <skill id="46399" name="Fall Damage/ Night Accuracy Decrease 60 per">
        <!--  -->
        <icon initial="icon.skill0000"/>
        <attributes/>
        <target/>
    </skill>
</list>
